{
  "mcpServers": {
	"filesystem": {
      "command": "npx",
      "args": ["-y", "@modelcontextprotocol/server-filesystem", "./admin-web/src", "./client-web/src", "./backend/src", "./docs"],
      "env": {}
    },  
    "github": {
      "command": "npx",
      "args": ["-y", "@modelcontextprotocol/server-github"],
      "env": {
        "GITHUB_PERSONAL_ACCESS_TOKEN": "${GITHUB_PERSONAL_ACCESS_TOKEN}"
      }
    },
	"context7": {
      "command": "npx",
      "args": ["-y", "@upstash/context7-mcp"],
      "env": {}
    },
	"token-optimizer": {
      "command": "npx",
      "args": ["-y", "token-optimizer-mcp"],
      "description": "Token optimization for 95%+ context reduction via content deduplication and compression"
    },
  }
}
